Workbook

Sheet Definición de la empresa
C2: Num | D2: Sueldo bruto/año (€) | E2: Coste salarial/año (€) | F2: TOTAL (€) | G2: Productividad | H2: Coste Directo (€) | I2: CI | J2: Coste Indirecto (€) | K2: Horas/año | L2: Horas productivas/año persona | M2: Horas productivas totales | N2: Precio hora (€)
B3: Jefe de Proyecto | C3: 1 | D3: 75000 | E3: 90527.17 | F3: =E3*C3 -> 90527.17 | G3: 0.7 | H3: =F3*G3 -> 63369.019 | I3: =100%-G3 -> 0.3 | J3: =F3*I3 -> 27158.151 | K3: 1756 | L3: =K3*G3 -> 1229.2 | M3: =L3*C3 -> 1229.2 | N3: =(H3/C3+$F$43/(1/M3*C3))/L3 -> 51.553058
B4: Arquitecto de Software | C4: 1 | D4: 58000 | E4: 73374.17 | F4: =E4*C4 -> 73374.17 | G4: 0.75 | H4: =F4*G4 -> 55030.628 | I4: =100%-G4 -> 0.25 | J4: =F4*I4 -> 18343.542 | K4: 1756 | L4: =K4*G4 -> 1317 | M4: =L4*C4 -> 1317 | N4: =(H4/C4+$F$43/(1/M4*C4))/L4 -> 41.784835
B5: Ingeniero de Software | C5: 2 | D5: 48000 | E5: 62784 | F5: =E5*C5 -> 125568 | G5: 0.8 | H5: =F5*G5 -> 100454.4 | I5: =100%-G5 -> 0.2 | J5: =F5*I5 -> 25113.6 | K5: 1756 | L5: =K5*G5 -> 1404.8 | M5: =L5*C5 -> 2809.6 | N5: =(H5/C5+$F$43/(1/M5*C5))/L5 -> 35.753986
B6: Tester | C6: 1 | D6: 35000 | E6: 45780 | F6: =E6*C6 -> 45780 | G6: 0.6 | H6: =F6*G6 -> 27468 | I6: =100%-G6 -> 0.4 | J6: =F6*I6 -> 18312 | K6: 1756 | L6: =K6*G6 -> 1053.6 | M6: =L6*C6 -> 1053.6 | N6: =(H6/C6+$F$43/(1/M6*C6))/L6 -> 26.070615
B7: TOTAL | C7: =SUM(C3:C6) -> 5 | F7: =SUM(F3:F6) -> 335249.34 | H7: =SUM(H3:H6) -> 246322.05 | J7: =SUM(J3:J6) -> 88927.293 | M7: =SUM(M3:M6) -> 6409.4

Sheet Partida 1 - Gestión proyecto
B2: Gestión del proyecto
B3: I 1 | C3: I 2 | D3: I3 | E3: Descripción | F3: Horas | G3: Coste/hora | H3: Precio (€) | I3: Total
B4: 1 | E4: Gestión de Proyecto e Inicio | I4: =SUM(H5:H6) -> 2591.2126
C5: 1 | D5: 1 | E5: Jefe de Proyecto | F5: 30 | G5: ='Definición de la empresa'!N3 -> 51.553058 | H5: =F5*G5 -> 1546.5917
D6: 2 | E6: Arquitecto de Software | F6: 25 | G6: ='Definición de la empresa'!N4 -> 41.784835 | H6: =F6*G6 -> 1044.6209
B8: 2 | E8: Análisis de requisitos | I8: =SUM(H9:H13) -> 5997.0863
C9: 1 | D9: 1 | E9: Jefe de Proyecto | F9: 30 | G9: ='Definición de la empresa'!N3 -> 51.553058 | H9: =F9*G9 -> 1546.5917
D10: 2 | E10: Arquitecto de Software | F10: 50 | G10: ='Definición de la empresa'!N4 -> 41.784835 | H10: =F10*G10 -> 2089.2417
D11: 3 | E11: Ingeniero de Software 1 | F11: 25 | G11: ='Definición de la empresa'!N5 -> 35.753986 | H11: =F11*G11 -> 893.84966
D12: 4 | E12: Ingeniero de Software 2 | F12: 25 | G12: ='Definición de la empresa'!N5 -> 35.753986 | H12: =F12*G12 -> 893.84966
D13: 5 | E13: Tester | F13: 22 | G13: ='Definición de la empresa'!N6 -> 26.070615 | H13: =F13*G13 -> 573.55353
B15: 3 | E15: Diseño y Arquitectura | I15: =SUM(H16:H20) -> 7236.3892
C16: 1 | D16: 1 | E16: Jefe de Proyecto | F16: 15 | G16: ='Definición de la empresa'!N3 -> 51.553058 | H16: =F16*G16 -> 773.29587
D17: 2 | E17: Arquitecto de Software | F17: 70 | G17: ='Definición de la empresa'!N4 -> 41.784835 | H17: =F17*G17 -> 2924.9384
D18: 3 | E18: Ingeniero de Software 1 | F18: 40 | G18: ='Definición de la empresa'!N5 -> 35.753986 | H18: =F18*G18 -> 1430.1595
D19: 4 | E19: Ingeniero de Software 2 | F19: 40 | G19: ='Definición de la empresa'!N5 -> 35.753986 | H19: =F19*G19 -> 1430.1595
D20: 5 | E20: Tester | F20: 26 | G20: ='Definición de la empresa'!N6 -> 26.070615 | H20: =F20*G20 -> 677.83599
B22: 4 | E22: Seguimiento y Control | I22: =SUM(H23:H27) -> 3610.4818
C23: 1 | D23: 1 | E23: Jefe de Proyecto | F23: 35 | G23: ='Definición de la empresa'!N3 -> 51.553058 | H23: =F23*G23 -> 1804.357
D24: 2 | E24: Arquitecto de Software | F24: 18 | G24: ='Definición de la empresa'!N4 -> 41.784835 | H24: =F24*G24 -> 752.12703
D25: 3 | E25: Ingeniero de Software 1 | F25: 10 | G25: ='Definición de la empresa'!N5 -> 35.753986 | H25: =F25*G25 -> 357.53986
D26: 4 | E26: Ingeniero de Software 2 | F26: 10 | G26: ='Definición de la empresa'!N5 -> 35.753986 | H26: =F26*G26 -> 357.53986
D27: 5 | E27: Tester | F27: 13 | G27: ='Definición de la empresa'!N6 -> 26.070615 | H27: =F27*G27 -> 338.918
B29: 5 | E29: Pruebas | I29: =SUM(H30:H32) -> 6636.8337
C30: 1 | D30: 1 | E30: Ingeniero de Software 1 | F30: 60 | G30: ='Definición de la empresa'!N5 -> 35.753986 | H30: =F30*G30 -> 2145.2392
D31: 2 | E31: Ingeniero de Software 2 | F31: 60 | G31: ='Definición de la empresa'!N5 -> 35.753986 | H31: =F31*G31 -> 2145.2392
D32: 3 | E32: Tester | F32: 90 | G32: ='Definición de la empresa'!N6 -> 26.070615 | H32: =F32*G32 -> 2346.3554
B34: 6 | E34: Documentación | I34: =SUM(H35:H36) -> 4764.5769
C35: 1 | D35: 1 | E35: Jefe de Proyecto | F35: 60 | G35: ='Definición de la empresa'!N3 -> 51.553058 | H35: =F35*G35 -> 3093.1835
D36: 2 | E36: Arquitecto de Software | F36: 40 | G36: ='Definición de la empresa'!N4 -> 41.784835 | H36: =F36*G36 -> 1671.3934
B38: 7 | E38: Cierre del Proyecto | I38: =SUM(H39) -> 1031.0612
C39: 1 | D39: 1 | E39: Jefe de Proyecto | F39: 20 | G39: ='Definición de la empresa'!N3 -> 51.553058 | H39: =F39*G39 -> 1031.0612
I40: =SUM(I4:I39) -> 31867.642

Sheet Partida 2 - Análisis sistema
B2: Análisis del sistema
B3: I 1 | C3: I 2 | D3: I3 | E3: Descripción | F3: Horas | G3: Coste/hora | H3: Precio (€) | I3: Total
B4: 1 | E4: Captura de requisitos | I4: =SUM(H5:H10) -> 3608.7141
C5: 1 | E5: Reuniones con el cliente
D6: 1 | E6: Jefe de Proyecto | F6: 20 | G6: ='Definición de la empresa'!N3 -> 51.553058 | H6: =F6*G6 -> 1031.0612
C7: 2 | E7: Análisis de necesidades
D8: 1 | E8: Jefe de Proyecto | F8: 25 | G8: ='Definición de la empresa'!N3 -> 51.553058 | H8: =F8*G8 -> 1288.8265
C9: 3 | E9: Validación de requisitos
D10: 1 | E10: Jefe de Proyecto | F10: 25 | G10: ='Definición de la empresa'!N3 -> 51.553058 | H10: =F10*G10 -> 1288.8265
B12: 2 | E12: Análisis funcional | I12: =SUM(H13:H26) -> 5148.574
C13: 1 | E13: Gestión de usuarios
D14: 1 | E14: Ingeniero de Software 1 | F14: 25 | G14: ='Definición de la empresa'!N5 -> 35.753986 | H14: =F14*G14 -> 893.84966
C15: 2 | E15: Sistema de publicaciones
D16: 1 | E16: Ingeniero de Software 1 | F16: 20 | G16: ='Definición de la empresa'!N5 -> 35.753986 | H16: =F16*G16 -> 715.07973
C17: 3 | E17: Sistema de compras
D18: 1 | E18: Ingeniero de Software 1 | F18: 23 | G18: ='Definición de la empresa'!N5 -> 35.753986 | H18: =F18*G18 -> 822.34169
C19: 4 | E19: Sistema de intercambios
D20: 1 | E20: Ingeniero de Software 2 | F20: 30 | G20: ='Definición de la empresa'!N5 -> 35.753986 | H20: =F20*G20 -> 1072.6196
C21: 5 | E21: Sistema de reviews
D22: 1 | E22: Ingeniero de Software 2 | F22: 15 | G22: ='Definición de la empresa'!N5 -> 35.753986 | H22: =F22*G22 -> 536.30979
C23: 6 | E23: Sistema de favoritos
D24: 1 | E24: Ingeniero de Software 2 | F24: 15 | G24: ='Definición de la empresa'!N5 -> 35.753986 | H24: =F24*G24 -> 536.30979
C25: 7 | E25: Sistema de carrito
D26: 1 | E26: Ingeniero de Software 2 | F26: 16 | G26: ='Definición de la empresa'!N5 -> 35.753986 | H26: =F26*G26 -> 572.06378
B28: 3 | E28: Diseño de datos | I28: =SUM(H29:H34) -> 3133.8626
C29: 1 | E29: Modelo entidad-relación
D30: 1 | E30: Arquitecto de Software | F30: 30 | G30: ='Definición de la empresa'!N4 -> 41.784835 | H30: =F30*G30 -> 1253.545
C31: 2 | E31: Revisión modelo BD
D32: 1 | E32: Arquitecto de Software | F32: 20 | G32: ='Definición de la empresa'!N4 -> 41.784835 | H32: =F32*G32 -> 835.6967
C33: 3 | E33: Diseño migraciones Flyway
D34: 1 | E34: Arquitecto de Software | F34: 25 | G34: ='Definición de la empresa'!N4 -> 41.784835 | H34: =F34*G34 -> 1044.6209
B36: 4 | E36: Análisis de seguridad | I36: =SUM(H37:H40) -> 1573.1754
C37: 1 | E37: Roles y permisos
D38: 1 | E38: Ingeniero de Software 1 | F38: 24 | G38: ='Definición de la empresa'!N5 -> 35.753986 | H38: =F38*G38 -> 858.09567
C39: 2 | E39: JWT y autenticación
D40: 1 | E40: Ingeniero de Software 2 | F40: 20 | G40: ='Definición de la empresa'!N5 -> 35.753986 | H40: =F40*G40 -> 715.07973
I41: =SUM(I4:I40) -> 13464.326

Sheet Partida 3 - Desarrollo
B2: Desarrollo
B3: I 1 | C3: I 2 | D3: I3 | E3: Descripción | F3: Horas | G3: Coste/hora | H3: Precio (€) | I3: Total
B4: 1 | E4: Base de Datos y Persistencia | I4: =SUM(H5:H7) -> 3459.0927
C5: 1 | D5: 1 | E5: Arquitecto de Software | F5: 40 | G5: ='Definición de la empresa'!N4 -> 41.784835 | H5: =F5*G5 -> 1671.3934
D6: 2 | E6: Ingeniero de Software 1 | F6: 25 | G6: ='Definición de la empresa'!N5 -> 35.753986 | H6: =F6*G6 -> 893.84966
D7: 3 | E7: Ingeniero de Software 2 | F7: 25 | G7: ='Definición de la empresa'!N5 -> 35.753986 | H7: =F7*G7 -> 893.84966
B9: 2 | E9: Backend Spring Boot | I9: =SUM(H10:H13) -> 7301.9277
C10: 1 | D10: 1 | E10: Arquitecto de Software | F10: 30 | G10: ='Definición de la empresa'!N4 -> 41.784835 | H10: =F10*G10 -> 1253.545
D11: 2 | E11: Ingeniero de Software 1 | F11: 70 | G11: ='Definición de la empresa'!N5 -> 35.753986 | H11: =F11*G11 -> 2502.779
D12: 3 | E12: Ingeniero de Software 2 | F12: 70 | G12: ='Definición de la empresa'!N5 -> 35.753986 | H12: =F12*G12 -> 2502.779
D13: 4 | E13: Tester | F13: 40 | G13: ='Definición de la empresa'!N6 -> 26.070615 | H13: =F13*G13 -> 1042.8246
B15: 3 | E15: Frontend Angular | I15: =SUM(H16:H19) -> 7301.9277
C16: 1 | D16: 1 | E16: Arquitecto de Software | F16: 30 | G16: ='Definición de la empresa'!N4 -> 41.784835 | H16: =F16*G16 -> 1253.545
D17: 2 | E17: Ingeniero de Software 1 | F17: 70 | G17: ='Definición de la empresa'!N5 -> 35.753986 | H17: =F17*G17 -> 2502.779
D18: 3 | E18: Ingeniero de Software 2 | F18: 70 | G18: ='Definición de la empresa'!N5 -> 35.753986 | H18: =F18*G18 -> 2502.779
D19: 4 | E19: Tester | F19: 40 | G19: ='Definición de la empresa'!N6 -> 26.070615 | H19: =F19*G19 -> 1042.8246
B21: 4 | E21: Seguridad JWT y Roles | I21: =SUM(H22:H24) -> 2205.5477
C22: 1 | D22: 1 | E22: Arquitecto de Software | F22: 10 | G22: ='Definición de la empresa'!N4 -> 41.784835 | H22: =F22*G22 -> 417.84835
D23: 2 | E23: Ingeniero de Software 1 | F23: 25 | G23: ='Definición de la empresa'!N5 -> 35.753986 | H23: =F23*G23 -> 893.84966
D24: 3 | E24: Ingeniero de Software 2 | F24: 25 | G24: ='Definición de la empresa'!N5 -> 35.753986 | H24: =F24*G24 -> 893.84966
I25: =SUM(H27:H29) -> 3776.5148
B26: 5 | E26: Pruebas Unitarias e Integración
C27: 1 | D27: 1 | E27: Tester | F27: 90 | G27: ='Definición de la empresa'!N6 -> 26.070615 | H27: =F27*G27 -> 2346.3554
D28: 2 | E28: Ingeniero de Software 1 | F28: 20 | G28: ='Definición de la empresa'!N5 -> 35.753986 | H28: =F28*G28 -> 715.07973
D29: 3 | E29: Ingeniero de Software 2 | F29: 20 | G29: ='Definición de la empresa'!N5 -> 35.753986 | H29: =F29*G29 -> 715.07973
I30: =SUM(I4:I29) -> 24045.011

Sheet Partida 4 - Despliegue
B2: Despliegue
B3: I 1 | C3: I 2 | D3: I3 | E3: Descripción | F3: Horas | G3: Coste/hora | H3: Precio (€) | I3: Total
B4: 1 | E4: Contenerización | I4: =SUM(H5:H8) -> 1671.3934
C5: 1 | E5: Docker Backend
D6: 1 | E6: Arquitecto de Software | F6: 20 | G6: ='Definición de la empresa'!N4 -> 41.784835 | H6: =F6*G6 -> 835.6967
C7: 2 | E7: Docker Frontend
D8: 1 | E8: Arquitecto de Software | F8: 20 | G8: ='Definición de la empresa'!N4 -> 41.784835 | H8: =F8*G8 -> 835.6967
B10: 2 | E10: CI/CD | I10: =SUM(H11:H18) -> 2028.9333
C11: 1 | E11: GitHub Actions Backend
D12: 1 | E12: Arquitecto de Software | F12: 10 | G12: ='Definición de la empresa'!N4 -> 41.784835 | H12: =F12*G12 -> 417.84835
D13: 2 | E13: Ingeniero de Software 1 | F13: 5 | G13: ='Definición de la empresa'!N5 -> 35.753986 | H13: =F13*G13 -> 178.76993
C14: 2 | E14: GitHub Actions Frontend
D15: 1 | E15: Arquitecto de Software | F15: 10 | G15: ='Definición de la empresa'!N4 -> 41.784835 | H15: =F15*G15 -> 417.84835
D16: 2 | E16: Ingeniero de Software 2 | F16: 5 | G16: ='Definición de la empresa'!N5 -> 35.753986 | H16: =F16*G16 -> 178.76993
C17: 3 | E17: Validación pipeline
D18: 1 | E18: Arquitecto de Software | F18: 20 | G18: ='Definición de la empresa'!N4 -> 41.784835 | H18: =F18*G18 -> 835.6967
B20: 3 | E20: Producción | I20: =SUM(H21:H29) -> 4876.5102
C21: 1 | E21: Despliegue Render
D22: 1 | E22: Arquitecto de Software | F22: 20 | G22: ='Definición de la empresa'!N4 -> 41.784835 | H22: =F22*G22 -> 835.6967
D23: 2 | E23: Ingeniero de Software 1 | F23: 20 | G23: ='Definición de la empresa'!N5 -> 35.753986 | H23: =F23*G23 -> 715.07973
C24: 2 | E24: PostgreSQL Producción
D25: 1 | E25: Arquitecto de Software | F25: 30 | G25: ='Definición de la empresa'!N4 -> 41.784835 | H25: =F25*G25 -> 1253.545
D26: 2 | E26: Ingeniero de Software 2 | F26: 20 | G26: ='Definición de la empresa'!N5 -> 35.753986 | H26: =F26*G26 -> 715.07973
C27: 3 | E27: Verificación despliegue
D28: 1 | E28: Arquitecto de Software | F28: 20 | G28: ='Definición de la empresa'!N4 -> 41.784835 | H28: =F28*G28 -> 835.6967
D29: 2 | E29: Tester | F29: 20 | G29: ='Definición de la empresa'!N6 -> 26.070615 | H29: =F29*G29 -> 521.4123
I30: =SUM(I4:I29) -> 8576.8368

Sheet Partida 5 - Material
B2: Material
B3: I 1 | C3: I 2 | D3: I3 | E3: Descripción | F3: Unidades | G3: Coste total (€) | H3: Coste anual | I3: Tipo | J3: Años
B4: 1 | E4: Equipos informáticos
C5: 1 | D5: 1 | E5: Equipo JP | F5: 1 | G5: 1000 | H5: =G5/J5 -> 200 | I5: Amortización | J5: 5
D6: 2 | E6: Equipo Arquitecto | F6: 1 | G6: 1000 | H6: =G6/J6 -> 200 | I6: Amortización | J6: 5
D7: 3 | E7: Equipo Ingeniero de Software 1 | F7: 1 | G7: 1000 | H7: =G7/J7 -> 200 | I7: Amortización | J7: 5
D8: 4 | E8: Equipo Ingeniero de Software 2 | F8: 1 | G8: 1000 | H8: =G8/J8 -> 200 | I8: Amortización | J8: 5
D9: 5 | E9: Equipo Tester | F9: 1 | G9: 1000 | H9: =G9/J9 -> 200 | I9: Amortización | J9: 5
B11: 2 | E11: Infraestructura cloud
C12: 1 | D12: 1 | E12: Hosting Frontend | F12: 1 | H12: 180 | I12: Alquiler
D13: 2 | E13: Hosting Backend | F13: 1 | H13: 300 | I13: Alquiler
D14: 3 | E14: PostgreSQL | F14: 1 | H14: 240 | I14: Alquiler
B16: 3 | E16: Dominio y certificados
C17: 1 | D17: 1 | E17: Dominio GameSwap | F17: 1 | G17: 20 | I17: Compra
D18: 2 | E18: Certificados SSL | F18: 1 | G18: 100 | I18: Compra
B20: 4 | E20: Keys APIs externas
C21: 1 | D21: 1 | E21: IGDB | F21: 1 | H21: 100 | I21: Alquiler
D22: 2 | E22: Stripe | F22: 1 | H22: 200 | I22: Alquiler
D23: 3 | E23: Sonar Cloud | F23: 1 | H23: 150 | I23: Alquiler
F24: Costes | G24: =SUM(G5:G23) -> 5120 | H24: =SUM(H5:H23) -> 2170

Sheet Partida 6 - Otros costes
B2: Otros costes
B3: I 1 | C3: I 2 | D3: I3 | E3: Descripción | F3: Horas | G3: Coste/hora | H3: Precio (€) | I3: Total
B4: 1 | E4: Formación | I4: =SUM(H4:H14) -> 3575.3986
C5: 1 | E5: Formación Angular
D6: 1 | E6: Ingeniero de Software 1 | F6: 20 | G6: ='Definición de la empresa'!N5 -> 35.753986 | H6: =F6*G6 -> 715.07973
D7: 2 | E7: Ingeniero de Software 2 | F7: 20 | G7: ='Definición de la empresa'!N5 -> 35.753986 | H7: =F7*G7 -> 715.07973
C8: 2 | E8: Formación Spring Boot
D9: 1 | E9: Ingeniero de Software 1 | F9: 20 | G9: ='Definición de la empresa'!N5 -> 35.753986 | H9: =F9*G9 -> 715.07973
D10: 2 | E10: Ingeniero de Software 2 | F10: 20 | G10: ='Definición de la empresa'!N5 -> 35.753986 | H10: =F10*G10 -> 715.07973
C11: 1 | E11: Formación DevOps
D12: 1 | E12: Ingeniero de Software 1 | F12: 10 | G12: ='Definición de la empresa'!N5 -> 35.753986 | H12: =F12*G12 -> 357.53986
D13: 2 | E13: Ingeniero de Software 2 | F13: 10 | G13: ='Definición de la empresa'!N5 -> 35.753986 | H13: =F13*G13 -> 357.53986
B15: 2 | E15: Documentación Final | I15: =SUM(H16:H23) -> 1371.5754
C16: 1 | E16: Memoria técnica
D17: 1 | E17: Arquitecto de Software | F17: 10 | G17: ='Definición de la empresa'!N4 -> 41.784835 | H17: =F17*G17 -> 417.84835
D18: 2 | E18: Ingeniero de Software 1 | F18: 5 | G18: ='Definición de la empresa'!N5 -> 35.753986 | H18: =F18*G18 -> 178.76993
D19: 3 | E19: Ingeniero de Software 2 | F19: 5 | G19: ='Definición de la empresa'!N5 -> 35.753986 | H19: =F19*G19 -> 178.76993
C20: 1 | E20: Manual usuario
D21: 1 | E21: Arquitecto de Software | F21: 4 | G21: ='Definición de la empresa'!N4 -> 41.784835 | H21: =F21*G21 -> 167.13934
D22: 2 | E22: Ingeniero de Software 1 | F22: 6 | G22: ='Definición de la empresa'!N5 -> 35.753986 | H22: =F22*G22 -> 214.52392
D23: 3 | E23: Ingeniero de Software 2 | F23: 6 | G23: ='Definición de la empresa'!N5 -> 35.753986 | H23: =F23*G23 -> 214.52392
I24: =SUM(I4:I23) -> 4946.974

Sheet Presupuesto de costes
B2: Presupuesto de costes
B3: Partida | C3: Coste
B4: Gestión del Proyecto | C4: ='Partida 1 - Gestión proyecto'!I40 -> 31867.642
B5: Análisis del Sistema | C5: ='Partida 2 - Análisis sistema'!I41 -> 13464.326
B6: Desarrollo | C6: ='Partida 3 - Desarrollo'!I30 -> 24045.011
B7: Despliegue | C7: ='Partida 4 - Despliegue'!I30 -> 8576.8368
B8: Material | C8: ='Partida 5 - Material'!G24 -> 5120
B9: Otros costes | C9: ='Partida 6 - Otros costes'!I24 -> 4946.974
B11: Coste de las partidas | C11: =SUM(C4:C9) -> 88020.789
B12: Beneficio empresarial 20% | C12: =C11*0.2 -> 17604.158
B14: Precio de venta al cliente | C14: =SUM(C11:C12) -> 105624.95

Sheet Presupuesto de cliente
B2: Presupuesto de cliente
B3: Partida | C3: Coste
B4: Análisis del Sistema | C4: ='Presupuesto de costes'!C5/('Presupuesto de costes'!C11-'Presupuesto de costes'!C4)*'Presupuesto de costes'!C14 -> 25326.608
B5: Desarrollo | C5: ='Presupuesto de costes'!C6/('Presupuesto de costes'!C11-'Presupuesto de costes'!C4)*'Presupuesto de costes'!C14 -> 45229.04
B6: Despliegue | C6: ='Presupuesto de costes'!C7/('Presupuesto de costes'!C11-'Presupuesto de costes'!C4)*'Presupuesto de costes'!C14 -> 16133.164
B7: Material | C7: ='Presupuesto de costes'!C8/('Presupuesto de costes'!C11-'Presupuesto de costes'!C4)*'Presupuesto de costes'!C14 -> 9630.7999
B8: Otros costes | C8: ='Presupuesto de costes'!C9/('Presupuesto de costes'!C11-'Presupuesto de costes'!C4)*'Presupuesto de costes'!C14 -> 9305.3354
B10: Precio de venta al cliente | C10: =SUM(C4:C8) -> 105624.95
